odoo/addons/crm_claim_analytic/README.rst
odoo/addons/crm_claim_analytic/__init__.py
odoo/addons/crm_claim_analytic/__manifest__.py
odoo/addons/crm_claim_analytic/i18n/crm_claim_analytic.pot
odoo/addons/crm_claim_analytic/i18n/es.po
odoo/addons/crm_claim_analytic/i18n/eu_ES.po
odoo/addons/crm_claim_analytic/i18n/it.po
odoo/addons/crm_claim_analytic/models/__init__.py
odoo/addons/crm_claim_analytic/models/account_analytic_account.py
odoo/addons/crm_claim_analytic/models/account_analytic_line.py
odoo/addons/crm_claim_analytic/models/crm_claim.py
odoo/addons/crm_claim_analytic/readme/CONTRIBUTORS.rst
odoo/addons/crm_claim_analytic/readme/DESCRIPTION.rst
odoo/addons/crm_claim_analytic/readme/USAGE.rst
odoo/addons/crm_claim_analytic/static/description/icon.png
odoo/addons/crm_claim_analytic/static/description/index.html
odoo/addons/crm_claim_analytic/tests/__init__.py
odoo/addons/crm_claim_analytic/tests/test_crm_claim_analytic.py
odoo/addons/crm_claim_analytic/views/account_analytic_account_views.xml
odoo/addons/crm_claim_analytic/views/account_analytic_line_views.xml
odoo/addons/crm_claim_analytic/views/crm_claim_views.xml
odoo_addon_crm_claim_analytic-16.0.1.0.0.5.dist-info/METADATA
odoo_addon_crm_claim_analytic-16.0.1.0.0.5.dist-info/WHEEL
odoo_addon_crm_claim_analytic-16.0.1.0.0.5.dist-info/top_level.txt
odoo_addon_crm_claim_analytic-16.0.1.0.0.5.dist-info/RECORD
